comet/__init__.py
comet/cli/compare.py
comet/cli/mbr.py
comet/cli/score.py
comet/cli/train.py
comet/encoders/__init__.py
comet/encoders/base.py
comet/encoders/bert.py
comet/encoders/minilm.py
comet/encoders/rembert.py
comet/encoders/xlmr.py
comet/encoders/xlmr_xl.py
comet/models/__init__.py
comet/models/base.py
comet/models/download_utils.py
comet/models/lru_cache.py
comet/models/metrics.py
comet/models/multitask/__init__.py
comet/models/multitask/unified_metric.py
comet/models/multitask/xcomet_metric.py
comet/models/pooling_utils.py
comet/models/predict_pbar.py
comet/models/predict_writer.py
comet/models/ranking/__init__.py
comet/models/ranking/ranking_metric.py
comet/models/regression/__init__.py
comet/models/regression/referenceless.py
comet/models/regression/regression_metric.py
comet/models/utils.py
comet/modules/__init__.py
comet/modules/feedforward.py
comet/modules/layerwise_attention.py
unbabel_comet-2.2.6.dist-info/LICENSE
unbabel_comet-2.2.6.dist-info/LICENSE.models.md
unbabel_comet-2.2.6.dist-info/METADATA
unbabel_comet-2.2.6.dist-info/WHEEL
unbabel_comet-2.2.6.dist-info/entry_points.txt
unbabel_comet-2.2.6.dist-info/RECORD
